<?xml version="1.0" encoding="utf-8"?>
<TextureAtlas imagePath="lime.png">
	<!-- Created with Adobe Animate version 22.0.6.202 -->
	<!-- http://www.adobe.com/products/animate.html -->
	<SubTexture name="lime0000" x="5" y="5" width="67" height="80"/>
	<SubTexture name="lime0001" x="5" y="5" width="67" height="80"/>
	<SubTexture name="lime0002" x="5" y="5" width="67" height="80"/>
	<SubTexture name="lime0003" x="77" y="5" width="67" height="80"/>
	<SubTexture name="lime0004" x="77" y="5" width="67" height="80"/>
	<SubTexture name="lime0005" x="77" y="5" width="67" height="80"/>
	<SubTexture name="lime0006" x="149" y="5" width="67" height="80"/>
	<SubTexture name="lime0007" x="149" y="5" width="67" height="80"/>
	<SubTexture name="lime0008" x="149" y="5" width="67" height="80"/>
	<SubTexture name="lime0009" x="221" y="5" width="67" height="80"/>
	<SubTexture name="lime0010" x="221" y="5" width="67" height="80"/>
	<SubTexture name="lime0011" x="221" y="5" width="67" height="80"/>
	<SubTexture name="lime0012" x="293" y="5" width="67" height="80"/>
	<SubTexture name="lime0013" x="293" y="5" width="67" height="80"/>
	<SubTexture name="lime0014" x="293" y="5" width="67" height="80"/>
	<SubTexture name="lime0015" x="365" y="5" width="67" height="80"/>
	<SubTexture name="lime0016" x="365" y="5" width="67" height="80"/>
	<SubTexture name="lime0017" x="365" y="5" width="67" height="80"/>
	<SubTexture name="lime0018" x="365" y="5" width="67" height="80"/>
	<SubTexture name="lime0019" x="365" y="5" width="67" height="80"/>
	<SubTexture name="lime0020" x="365" y="5" width="67" height="80"/>
	<SubTexture name="lime0021" x="365" y="5" width="67" height="80"/>
	<SubTexture name="lime0022" x="365" y="5" width="67" height="80"/>
	<SubTexture name="lime0023" x="365" y="5" width="67" height="80"/>
	<SubTexture name="lime0024" x="365" y="5" width="67" height="80"/>
	<SubTexture name="lime0025" x="365" y="5" width="67" height="80"/>
	<SubTexture name="lime0026" x="365" y="5" width="67" height="80"/>
	<SubTexture name="lime0027" x="365" y="5" width="67" height="80"/>
	<SubTexture name="lime0028" x="365" y="5" width="67" height="80"/>
	<SubTexture name="lime0029" x="365" y="5" width="67" height="80"/>
	<SubTexture name="lime0030" x="365" y="5" width="67" height="80"/>
	<SubTexture name="lime0031" x="365" y="5" width="67" height="80"/>
	<SubTexture name="lime0032" x="365" y="5" width="67" height="80"/>
	<SubTexture name="lime0033" x="365" y="5" width="67" height="80"/>
	<SubTexture name="lime0034" x="365" y="5" width="67" height="80"/>
	<SubTexture name="lime0035" x="365" y="5" width="67" height="80"/>
	<SubTexture name="lime0036" x="365" y="5" width="67" height="80"/>
	<SubTexture name="lime0037" x="365" y="5" width="67" height="80"/>
	<SubTexture name="lime0038" x="365" y="5" width="67" height="80"/>
	<SubTexture name="lime0039" x="365" y="5" width="67" height="80"/>
	<SubTexture name="lime0040" x="365" y="5" width="67" height="80"/>
	<SubTexture name="lime0041" x="365" y="5" width="67" height="80"/>
	<SubTexture name="lime0042" x="437" y="5" width="67" height="80"/>
	<SubTexture name="lime0043" x="437" y="5" width="67" height="80"/>
	<SubTexture name="lime0044" x="437" y="5" width="67" height="80"/>
	<SubTexture name="lime0045" x="5" y="90" width="67" height="80"/>
	<SubTexture name="lime0046" x="5" y="90" width="67" height="80"/>
	<SubTexture name="lime0047" x="5" y="90" width="67" height="80"/>
	<SubTexture name="lime0048" x="77" y="90" width="67" height="80"/>
	<SubTexture name="lime0049" x="77" y="90" width="67" height="80"/>
	<SubTexture name="lime0050" x="77" y="90" width="67" height="80"/>
	<SubTexture name="lime0051" x="149" y="90" width="67" height="80"/>
	<SubTexture name="lime0052" x="149" y="90" width="67" height="80"/>
	<SubTexture name="lime0053" x="149" y="90" width="67" height="80"/>
	<SubTexture name="lime0054" x="221" y="90" width="67" height="80"/>
	<SubTexture name="lime0055" x="221" y="90" width="67" height="80"/>
	<SubTexture name="lime0056" x="221" y="90" width="67" height="80"/>
	<SubTexture name="lime0057" x="221" y="90" width="67" height="80"/>
	<SubTexture name="lime0058" x="221" y="90" width="67" height="80"/>
	<SubTexture name="lime0059" x="221" y="90" width="67" height="80"/>
	<SubTexture name="lime0060" x="221" y="90" width="67" height="80"/>
	<SubTexture name="lime0061" x="221" y="90" width="67" height="80"/>
	<SubTexture name="lime0062" x="221" y="90" width="67" height="80"/>
	<SubTexture name="lime0063" x="221" y="90" width="67" height="80"/>
	<SubTexture name="lime0064" x="221" y="90" width="67" height="80"/>
	<SubTexture name="lime0065" x="221" y="90" width="67" height="80"/>
	<SubTexture name="lime0066" x="221" y="90" width="67" height="80"/>
	<SubTexture name="lime0067" x="221" y="90" width="67" height="80"/>
	<SubTexture name="lime0068" x="221" y="90" width="67" height="80"/>
	<SubTexture name="lime0069" x="221" y="90" width="67" height="80"/>
	<SubTexture name="lime0070" x="221" y="90" width="67" height="80"/>
	<SubTexture name="lime0071" x="221" y="90" width="67" height="80"/>
	<SubTexture name="lime0072" x="221" y="90" width="67" height="80"/>
	<SubTexture name="lime0073" x="221" y="90" width="67" height="80"/>
	<SubTexture name="lime0074" x="221" y="90" width="67" height="80"/>
	<SubTexture name="lime0075" x="221" y="90" width="67" height="80"/>
	<SubTexture name="lime0076" x="221" y="90" width="67" height="80"/>
	<SubTexture name="lime0077" x="221" y="90" width="67" height="80"/>
	<SubTexture name="lime0078" x="221" y="90" width="67" height="80"/>
	<SubTexture name="lime0079" x="221" y="90" width="67" height="80"/>
	<SubTexture name="lime0080" x="221" y="90" width="67" height="80"/>
	<SubTexture name="lime0081" x="293" y="90" width="67" height="80"/>
	<SubTexture name="lime0082" x="293" y="90" width="67" height="80"/>
	<SubTexture name="lime0083" x="293" y="90" width="67" height="80"/>
	<SubTexture name="lime0084" x="365" y="90" width="67" height="80"/>
	<SubTexture name="lime0085" x="365" y="90" width="67" height="80"/>
	<SubTexture name="lime0086" x="365" y="90" width="67" height="80"/>
	<SubTexture name="lime0087" x="437" y="90" width="67" height="80"/>
	<SubTexture name="lime0088" x="437" y="90" width="67" height="80"/>
	<SubTexture name="lime0089" x="437" y="90" width="67" height="80"/>
	<SubTexture name="lime0090" x="437" y="90" width="67" height="80"/>
	<SubTexture name="lime0091" x="5" y="175" width="67" height="80"/>
	<SubTexture name="lime0092" x="5" y="175" width="67" height="80"/>
	<SubTexture name="lime0093" x="5" y="175" width="67" height="80"/>
	<SubTexture name="lime0094" x="5" y="175" width="67" height="80"/>
	<SubTexture name="lime0095" x="77" y="175" width="67" height="80"/>
	<SubTexture name="lime0096" x="77" y="175" width="67" height="80"/>
	<SubTexture name="lime0097" x="77" y="175" width="67" height="80"/>
	<SubTexture name="lime0098" x="149" y="175" width="67" height="80"/>
	<SubTexture name="lime0099" x="149" y="175" width="67" height="80"/>
	<SubTexture name="lime0100" x="149" y="175" width="67" height="80"/>
	<SubTexture name="lime0101" x="221" y="175" width="67" height="80"/>
	<SubTexture name="lime0102" x="221" y="175" width="67" height="80"/>
	<SubTexture name="lime0103" x="221" y="175" width="67" height="80"/>
	<SubTexture name="lime0104" x="221" y="175" width="67" height="80"/>
	<SubTexture name="lime0105" x="221" y="175" width="67" height="80"/>
	<SubTexture name="lime0106" x="221" y="175" width="67" height="80"/>
</TextureAtlas>
