{
	"animations": [
		{
			"loop": false,
			"offsets": [
				0,
				0
			],
			"anim": "idle",
			"fps": 24,
			"name": "idle",
			"indices": []
		},
		{
			"loop": false,
			"offsets": [
				0,
				0
			],
			"anim": "singLEFT",
			"fps": 24,
			"name": "left",
			"indices": []
		},
		{
			"loop": false,
			"offsets": [
				0,
				0
			],
			"anim": "singDOWN",
			"fps": 24,
			"name": "down",
			"indices": []
		},
		{
			"loop": false,
			"offsets": [
				0,
				0
			],
			"anim": "singUP",
			"fps": 24,
			"name": "up",
			"indices": []
		},
		{
			"loop": false,
			"offsets": [
				0,
				0
			],
			"anim": "singRIGHT",
			"fps": 22,
			"name": "right",
			"indices": []
		}
	],
	"no_antialiasing": true,
	"image": "characters/terminated/henry3",
	"position": [
		0,
		0
	],
	"healthicon": "termin",
	"flip_x": false,
	"healthbar_colors": [
		56,
		56,
		56
	],
	"camera_position": [
		-155,
		100
	],
	"sing_duration": 4,
	"scale": 1
}